avery_Trading_ML/__init__.py
avery_Trading_ML-0.8.0.dist-info/LICENSE
avery_Trading_ML-0.8.0.dist-info/METADATA
avery_Trading_ML-0.8.0.dist-info/WHEEL
avery_Trading_ML-0.8.0.dist-info/top_level.txt
avery_Trading_ML-0.8.0.dist-info/RECORD
